{
  "update": [
    true
  ],
  "team": [
    {
      "id": 0,
      "name": "Léo DRAGUY",
      "job": "Président",
      "subject": "ut",
      "age": 24,
      "description": "Excellent dessinateur menant l'association d'une main de fer.",
      "drawingTechnique": "Traditionnelle et tablette",
      "publicationNb": 2
    },
    {
      "id": 1,
      "name": "Anthony MAI",
      "job": "Vice-président",
      "subject": "illo",
      "age": 20,
      "description": "Il adore dormir mais il est toujours au rapport pour les réunions.",
      "drawingTechnique": "Traditionnelle",
      "publicationNb": 5
    },
    {
      "id": 2,
      "name": "Hana TENDA",
      "job": "Trésorière",
      "subject": "aut",
      "age": 25,
      "description": "Sérieuse et consciencieuse, elle est la gardienne des trésor de l'association.",
      "drawingTechnique": "Tablette",
      "publicationNb": 4
    }
  ],
  "members": [
    {
      "id": 0,
      "name": "Danyka",
      "job": "Réalise les croquis des planches pour les BD.",
      "subject": "accusantium",
      "age": 21,
      "description": "Dessinant plus vite que son ombre, elle peut vous sortir le croquis de 10 planches de BD par heure, et encore plus si vous lui apportez un paquet de bonbon.",
      "drawingTechnique": "Traditionnelle",
      "publicationNb": 2
    },
    {
      "id": 1,
      "name": "Brad",
      "job": "Character designer",
      "subject": "et",
      "age": 22,
      "description": "Doté d'une imagination débordante, il adore créer des personnages de tous univers, avec une préférence pour le cyberpunk et tout ce qui est futuriste.",
      "drawingTechnique": "Traditionnelle et tablette",
      "publicationNb": 4
    },
    {
      "id": 2,
      "name": "Bradley",
      "job": "Création de décors",
      "subject": "perferendis",
      "age": 21,
      "description": "Membre spécialisé dans le dessin de paysages, en particulier de grandes villes au style futuriste. Il réalise ses croquis en technique tradtionnelle avant de toute passer sur ordinateur pour le line et la couleur.",
      "drawingTechnique": "Traditionnelle et tablette",
      "publicationNb": 5
    },
    {
      "id": 3,
      "name": "Berniece",
      "job": "quae",
      "subject": "dolores",
      "age": 23,
      "description": "quasi quibusdam eum",
      "drawingTechnique": "Tablette",
      "publicationNb": 1
    },
    {
      "id": 4,
      "name": "Rene",
      "job": "nihil",
      "subject": "amet",
      "age": 22,
      "description": "non",
      "drawingTechnique": "harum",
      "publicationNb": 4
    },
    {
      "id": 5,
      "name": "Justen",
      "job": "molestias",
      "subject": "ducimus",
      "age": 24,
      "description": "dolorem accusantium",
      "drawingTechnique": "illo",
      "publicationNb": 3
    },
    {
      "id": 6,
      "name": "Cleo",
      "job": "optio",
      "subject": "qui",
      "age": 22,
      "description": "recusandae nam et ea unde qui",
      "drawingTechnique": "itaque",
      "publicationNb": 3
    },
    {
      "id": 7,
      "name": "Elfrieda",
      "job": "illo",
      "subject": "quis",
      "age": 21,
      "description": "itaque vel laudantium",
      "drawingTechnique": "necessitatibus",
      "publicationNb": 4
    },
    {
      "id": 8,
      "name": "Abdiel",
      "job": "et",
      "subject": "dolores",
      "age": 22,
      "description": "velit",
      "drawingTechnique": "qui",
      "publicationNb": 4
    },
    {
      "id": 9,
      "name": "Zander",
      "job": "adipisci",
      "subject": "minima",
      "age": 21,
      "description": "consequatur eligendi molestias quia",
      "drawingTechnique": "blanditiis",
      "publicationNb": 3
    },
    {
      "id": 10,
      "name": "Zita",
      "job": "rem",
      "subject": "aut",
      "age": 24,
      "description": "id commodi velit",
      "drawingTechnique": "quae",
      "publicationNb": 5
    },
    {
      "id": 11,
      "name": "Mayra",
      "job": "harum",
      "subject": "consequatur",
      "age": 24,
      "description": "saepe",
      "drawingTechnique": "repellendus",
      "publicationNb": 2
    },
    {
      "id": 12,
      "name": "Mandy",
      "job": "sed",
      "subject": "minus",
      "age": 25,
      "description": "impedit molestias maxime corporis ad",
      "drawingTechnique": "exercitationem",
      "publicationNb": 4
    },
    {
      "id": 13,
      "name": "Alphonso",
      "job": "aut",
      "subject": "vero",
      "age": 21,
      "description": "repellendus id eum",
      "drawingTechnique": "molestiae",
      "publicationNb": 4
    },
    {
      "id": 14,
      "name": "Murl",
      "job": "quibusdam",
      "subject": "repellendus",
      "age": 24,
      "description": "fugiat velit",
      "drawingTechnique": "libero",
      "publicationNb": 5
    },
    {
      "id": 15,
      "name": "Josiah",
      "job": "reiciendis",
      "subject": "assumenda",
      "age": 21,
      "description": "ullam aliquam quae error",
      "drawingTechnique": "dolor",
      "publicationNb": 2
    },
    {
      "id": 16,
      "name": "Arno",
      "job": "officiis",
      "subject": "dolore",
      "age": 22,
      "description": "sed quaerat et accusamus",
      "drawingTechnique": "temporibus",
      "publicationNb": 4
    },
    {
      "id": 17,
      "name": "Sheldon",
      "job": "perferendis",
      "subject": "necessitatibus",
      "age": 24,
      "description": "vitae rerum officia atque enim",
      "drawingTechnique": "voluptatem",
      "publicationNb": 4
    },
    {
      "id": 18,
      "name": "Monte",
      "job": "est",
      "subject": "tempora",
      "age": 20,
      "description": "architecto consequatur quia eos voluptas",
      "drawingTechnique": "nobis",
      "publicationNb": 3
    },
    {
      "id": 19,
      "name": "Brandt",
      "job": "alias",
      "subject": "et",
      "age": 24,
      "description": "sit est",
      "drawingTechnique": "ut",
      "publicationNb": 1
    },
    {
      "id": 20,
      "name": "Raleigh",
      "job": "soluta",
      "subject": "omnis",
      "age": 23,
      "description": "ut et eligendi unde et",
      "drawingTechnique": "repellendus",
      "publicationNb": 4
    }
  ],
  "events": [
    {
      "id": 0,
      "name": "aperiam temporibus exercitationem aut et",
      "description": "rerum praesentium aut perferendis laudantium rerum esse inventore aut non aliquid"
    },
    {
      "id": 1,
      "name": "quia eligendi voluptas sunt veritatis fugiat",
      "description": "nulla delectus ut molestias atque similique temporibus culpa placeat commodi corporis aut ab vel ad animi"
    },
    {
      "id": 2,
      "name": "in ex nemo occaecati",
      "description": "dolor quas asperiores veritatis id molestiae qui repellendus ipsa quod reiciendis unde similique nisi voluptates vel mollitia"
    },
    {
      "id": 3,
      "name": "porro error in",
      "description": "et necessitatibus praesentium enim minus autem dolorem soluta cum voluptas modi eaque non aut nihil eum doloribus autem qui debitis"
    },
    {
      "id": 4,
      "name": "modi voluptatem quibusdam ab est facilis laudantium",
      "description": "dolor praesentium voluptate laudantium aut velit vel impedit dignissimos aut dolore ipsam necessitatibus ipsum suscipit"
    },
    {
      "id": 5,
      "name": "eum voluptatem explicabo hic",
      "description": "maxime cumque aut quasi blanditiis quidem qui et qui nisi iure velit autem"
    }
  ],
  "tasks": [
    {
      "id": 0,
      "idMember": 2,
      "tasks": "Préparer la note de réunion pour la Festival Pulp",
      "dueDate": "2019-04-06",
      "category": "reunion",
      "description": "quia sint architecto necessitatibus inventore fugit omnis consectetur quis perspiciatis aut et voluptatem dolor quibusdam praesentium ipsam voluptatem velit porro voluptas",
      "action": {
        "displayDescription": false,
        "displayPopUp": false
      },
      "isDone": false
    },
    {
      "id": 1,
      "idMember": 2,
      "tasks": "Impression des affiches du Festival Pulp",
      "dueDate": "2019-03-20",
      "category": "communication",
      "description": "iste officiis eum aut voluptatum velit officia fugit pariatur a ut aliquam eligendi libero necessitatibus",
      "action": {
        "displayDescription": false,
        "displayPopUp": false
      },
      "isDone": true
    },
    {
      "id": 2,
      "idMember": 21,
      "tasks": "Rédaction du compte-rendu de la réunion du 10/03/2019",
      "dueDate": "2019-03-12",
      "category": "reunion",
      "description": "atque ut qui blanditiis eum officia consequuntur harum aspernatur aut doloribus qui delectus quos autem optio",
      "action": {
        "displayDescription": false,
        "displayPopUp": false
      },
      "isDone": false
    },
    {
      "id": 3,
      "idMember": 11,
      "tasks": "fugit quaerat consequatur sint vel veritatis eaque non",
      "dueDate": "1978-12-13",
      "category": "communication",
      "description": "omnis assumenda dolorem fuga aperiam consequatur perspiciatis eos est voluptatem minima quas reiciendis consequatur",
      "action": {
        "displayDescription": false,
        "displayPopUp": false
      },
      "isDone": true
    },
    {
      "id": 4,
      "idMember": 15,
      "tasks": "minus accusantium aut voluptates",
      "dueDate": "1997-11-17",
      "category": "communication",
      "description": "eum voluptas neque et voluptates voluptas pariatur quas consequuntur assumenda modi tenetur sit ex tempore vero sit",
      "action": {
        "displayDescription": false,
        "displayPopUp": false
      },
      "isDone": false
    },
    {
      "id": 5,
      "idMember": 4,
      "tasks": "Maquette finale du fanzine",
      "dueDate": "2019-03-06",
      "category": "fanzine",
      "description": "iste et accusantium aspernatur aut voluptatem voluptatibus consectetur vel temporibus et labore iusto",
      "action": {
        "displayDescription": false,
        "displayPopUp": false
      },
      "isDone": false
    },
    {
      "id": 6,
      "idMember": 9,
      "tasks": "id eius quis velit",
      "dueDate": "1986-02-04",
      "category": "communication",
      "description": "ut eum atque corrupti suscipit unde est laboriosam modi ut et voluptatum aut repellendus qui voluptas",
      "action": {
        "displayDescription": false,
        "displayPopUp": false
      },
      "isDone": false
    },
    {
      "id": 7,
      "idMember": 17,
      "tasks": "cum iste provident voluptas occaecati laborum eum",
      "dueDate": "1974-12-13",
      "category": "communication",
      "description": "voluptas soluta unde magnam eligendi alias reiciendis aut repellendus in quas officiis consequatur et sunt sed",
      "action": {
        "displayDescription": false,
        "displayPopUp": false
      },
      "isDone": false
    },
    {
      "id": 8,
      "idMember": 18,
      "tasks": "provident omnis eligendi odit ducimus blanditiis ab",
      "dueDate": "1996-08-30",
      "category": "fanzine",
      "description": "voluptates veniam necessitatibus tempore rerum ut sequi impedit atque sequi quidem officia recusandae impedit sit beatae odio quo nisi ratione quasi",
      "action": {
        "displayDescription": false,
        "displayPopUp": false
      },
      "isDone": false
    },
    {
      "id": 9,
      "idMember": 4,
      "tasks": "voluptatem delectus et maxime sit laborum",
      "dueDate": "1990-12-22",
      "category": "fanzine",
      "description": "corrupti eligendi molestias aut beatae qui quae quas debitis voluptatem corporis quae rerum libero voluptatum voluptates corrupti laboriosam dolor fugiat velit magnam id",
      "action": {
        "displayDescription": false,
        "displayPopUp": false
      },
      "isDone": false
    },
    {
      "id": 10,
      "idMember": 12,
      "tasks": "rem asperiores eos voluptatem nemo et sunt",
      "dueDate": "1992-10-05",
      "category": "fanzine",
      "description": "id cumque ab nostrum corporis occaecati iure aliquam possimus maiores dolorem sapiente cumque atque et laboriosam dolor explicabo quia a ut ipsum qui",
      "action": {
        "displayDescription": false,
        "displayPopUp": false
      },
      "isDone": false
    }
  ],
  "news": [
    {
      "id": 0,
      "name": "Recrutement équipe 2020",
      "date": "2019-05-01",
      "description": "Graphite recherche de nouveaux dessinateurs pour intégrer l'équipe de 2020 ! Séances créatives, bonne humeur et partage sont au rendez-vous !"
    },
    {
      "id": 1,
      "name": "Festival Pulp édition 2020",
      "date": "2019-04-06",
      "description": "Le festival Pulp vient à peine de se terminer que nous préparons la prochaine édition. Notez dès à présent les dates : du 3 à 5 avril 2020 !"
    },
    {
      "id": 2,
      "name": "Dernière ligne droite avant le festival Pulp",
      "date": "2019-03-20",
      "description": "Le festival Pulp approche à grands pas ! Venez découvrir nos artistes et leur fanzine les 6 et 7 avril prochain !"
    },
    {
      "id": 3,
      "name": "Programme du festival Pulp",
      "date": "2019-02-19",
      "description": "Le programme du festival est en ligne ! Animations, échanges, ateliers, nous vous avons concocté plein d'activités !"
    },
    {
      "id": 4,
      "name": "quia non",
      "date": "2019-02-10",
      "description": "aut sapiente facere tempora"
    },
    {
      "id": 5,
      "name": "explicabo et ullam sint",
      "date": "2019-01-04",
      "description": "architecto ab aut dolor nam"
    },
    {
      "id": 6,
      "name": "voluptatem aut",
      "date": "2018-12-31",
      "description": "labore"
    },
    {
      "id": 7,
      "name": "adipisci delectus eum dicta et",
      "date": "2018-12-18",
      "description": "dolore et voluptatum praesentium"
    },
    {
      "id": 8,
      "name": "dolores quis cum vitae non",
      "date": "2018-12-01",
      "description": "ducimus quidem"
    },
    {
      "id": 9,
      "name": "tempore recusandae expedita deleniti",
      "date": "2018-10-31",
      "description": "et voluptate consequatur itaque"
    },
    {
      "id": 10,
      "name": "quae unde qui amet",
      "date": "2018-10-22",
      "description": "cupiditate ullam"
    }
  ],
  "userAction": {
    "task": {
      "displayPopUp": false,
      "taskName": "",
      "taskDescription": "",
      "taskDate": "",
      "taskCategory": "none",
      "communication": false,
      "fanzine": false,
      "reunion": false
    }
  }
}
